FeynmanAI/CacheRAG.py
FeynmanAI/DOCXToDocument.py
FeynmanAI/PPTXToDocument.py
FeynmanAI/PromptTemplates.py
FeynmanAI/RAGPipeline.py
FeynmanAI/RAGPreprocessor.py
FeynmanAI/Spinner.py
FeynmanAI/__init__.py
FeynmanAI/__main__.py
FeynmanAI/rag_cli.py
FeynmanAI/utils.py
FeynmanAI-0.1.4.dist-info/METADATA
FeynmanAI-0.1.4.dist-info/WHEEL
FeynmanAI-0.1.4.dist-info/entry_points.txt
FeynmanAI-0.1.4.dist-info/top_level.txt
FeynmanAI-0.1.4.dist-info/RECORD
